{
  "models": [
    {
      "id": "ima_20260214T204248_5cls",
      "type": "image",
      "name": "daisy, dandelion, rose",
      "classes": [
        "daisy",
        "dandelion",
        "rose",
        "sunflower",
        "tulip"
      ],
      "accuracy": 0.9472727272727273,
      "trained_at": "2026-02-14T20:42:48.147458",
      "active": false,
      "path": "D:\\Akshay's Stuff\\Smart glasses\\Akshay-object-detection-with-OpenCV\\trained_models\\models\\ima_20260214T204248_5cls",
      "meta": {
        "classes": [
          "daisy",
          "dandelion",
          "rose",
          "sunflower",
          "tulip"
        ],
        "img_size": 224,
        "accuracy": 0.9472727272727273,
        "trained_at": "2026-02-14T20:42:48.147458",
        "model_type": "classifier"
      }
    },
    {
      "id": "ima_20260215_193128_archive_(14)_(1)_75cls",
      "type": "image",
      "name": "Archive (14) (1)",
      "classes": [
        "adonis",
        "african_giant_swallowtail",
        "american_snoot",
        "an_88",
        "appollo",
        "atala",
        "banded_orange_heliconian",
        "banded_peacock",
        "beckers_white",
        "black_hairstreak",
        "blue_morpho",
        "blue_spotted_crow",
        "brown_siproeta",
        "cabbage_white",
        "cairns_birdwing",
        "checquered_skipper",
        "chestnut",
        "cleopatra",
        "clodius_parnassian",
        "clouded_sulphur",
        "common_banded_awl",
        "common_wood-nymph",
        "copper_tail",
        "crecent",
        "crimson_patch",
        "danaid_eggfly",
        "eastern_coma",
        "eastern_dapple_white",
        "eastern_pine_elfin",
        "elbowed_pierrot",
        "gold_banded",
        "great_eggfly",
        "great_jay",
        "green_celled_cattleheart",
        "grey_hairstreak",
        "indra_swallow",
        "iphiclus_sister",
        "julia",
        "large_marble",
        "malachite",
        "mangrove_skipper",
        "mestra",
        "metalmark",
        "milberts_tortoiseshell",
        "monarch",
        "mourning_cloak",
        "orange_oakleaf",
        "orange_tip",
        "orchard_swallow",
        "painted_lady",
        "paper_kite",
        "peacock",
        "pine_white",
        "pipevine_swallow",
        "popinjay",
        "purple_hairstreak",
        "purplish_copper",
        "question_mark",
        "red_admiral",
        "red_cracker",
        "red_postman",
        "red_spotted_purple",
        "scarce_swallow",
        "silver_spot_skipper",
        "sleepy_orange",
        "sootywing",
        "southern_dogface",
        "straited_queen",
        "tropical_leafwing",
        "two_barred_flasher",
        "ulyses",
        "viceroy",
        "wood_satyr",
        "yellow_swallow_tail",
        "zebra_long_wing"
      ],
      "accuracy": 0.6036618201400108,
      "trained_at": "2026-02-15T19:31:28.598866",
      "active": true,
      "path": "D:\\Akshay's Stuff\\Smart glasses\\Akshay-object-detection-with-OpenCV\\trained_models\\models\\ima_20260215_193128_archive_(14)_(1)_75cls",
      "meta": {
        "classes": [
          "adonis",
          "african_giant_swallowtail",
          "american_snoot",
          "an_88",
          "appollo",
          "atala",
          "banded_orange_heliconian",
          "banded_peacock",
          "beckers_white",
          "black_hairstreak",
          "blue_morpho",
          "blue_spotted_crow",
          "brown_siproeta",
          "cabbage_white",
          "cairns_birdwing",
          "checquered_skipper",
          "chestnut",
          "cleopatra",
          "clodius_parnassian",
          "clouded_sulphur",
          "common_banded_awl",
          "common_wood-nymph",
          "copper_tail",
          "crecent",
          "crimson_patch",
          "danaid_eggfly",
          "eastern_coma",
          "eastern_dapple_white",
          "eastern_pine_elfin",
          "elbowed_pierrot",
          "gold_banded",
          "great_eggfly",
          "great_jay",
          "green_celled_cattleheart",
          "grey_hairstreak",
          "indra_swallow",
          "iphiclus_sister",
          "julia",
          "large_marble",
          "malachite",
          "mangrove_skipper",
          "mestra",
          "metalmark",
          "milberts_tortoiseshell",
          "monarch",
          "mourning_cloak",
          "orange_oakleaf",
          "orange_tip",
          "orchard_swallow",
          "painted_lady",
          "paper_kite",
          "peacock",
          "pine_white",
          "pipevine_swallow",
          "popinjay",
          "purple_hairstreak",
          "purplish_copper",
          "question_mark",
          "red_admiral",
          "red_cracker",
          "red_postman",
          "red_spotted_purple",
          "scarce_swallow",
          "silver_spot_skipper",
          "sleepy_orange",
          "sootywing",
          "southern_dogface",
          "straited_queen",
          "tropical_leafwing",
          "two_barred_flasher",
          "ulyses",
          "viceroy",
          "wood_satyr",
          "yellow_swallow_tail",
          "zebra_long_wing"
        ],
        "img_size": 224,
        "accuracy": 0.6036618201400108,
        "trained_at": "2026-02-15T19:31:28.576132",
        "model_type": "classifier"
      }
    }
  ]
}